[{"CreationTime":"2022-11-11T14:01:54.740522+01:00","Name":"0","AdditionalInformation":"000501","MeasurementName":null},{"CreationTime":"2022-11-25T12:21:25.788159+01:00","Name":"0","AdditionalInformation":"100919","MeasurementName":null},{"CreationTime":"2022-12-21T13:09:34.042164+01:00","Name":"0","AdditionalInformation":"100919","MeasurementName":null},{"CreationTime":"2023-01-02T10:04:09.580103+01:00","Name":"0","AdditionalInformation":"100919","MeasurementName":null},{"CreationTime":"2023-01-03T13:55:30.577702+01:00","Name":"0","AdditionalInformation":"000501","MeasurementName":null},{"CreationTime":"2023-03-20T11:31:17.813161+01:00","Name":"0","AdditionalInformation":"100919","MeasurementName":null},{"CreationTime":"2023-03-20T11:37:10.904373+01:00","Name":"0","AdditionalInformation":"100919","MeasurementName":null},{"CreationTime":"2023-03-20T11:42:24.948991+01:00","Name":"0","AdditionalInformation":"100919","MeasurementName":null},{"CreationTime":"2023-03-20T14:50:21.212197+01:00","Name":"0","AdditionalInformation":"000501","MeasurementName":null},{"CreationTime":"2023-03-20T14:55:09.419961+01:00","Name":"0","AdditionalInformation":"000501","MeasurementName":null},{"CreationTime":"2023-03-20T15:08:37.257191+01:00","Name":"0","AdditionalInformation":"000501","MeasurementName":null},{"CreationTime":"2023-03-20T15:12:57.568648+01:00","Name":"0","AdditionalInformation":"000501","MeasurementName":null},{"CreationTime":"2023-06-21T10:16:00.939435+02:00","Name":"0","AdditionalInformation":"000402","MeasurementName":null},{"CreationTime":"2023-06-27T08:39:31.857723+02:00","Name":"0","AdditionalInformation":"000402","MeasurementName":null},{"CreationTime":"2023-08-04T11:03:35.724323+02:00","Name":"0","AdditionalInformation":"000402","MeasurementName":null},{"CreationTime":"2023-08-04T11:04:38.783944+02:00","Name":"0","AdditionalInformation":"000402","MeasurementName":null},{"CreationTime":"2023-09-25T14:26:04.12567+02:00","Name":"0","AdditionalInformation":"000501","MeasurementName":null},{"CreationTime":"2023-09-26T07:35:46.15801+02:00","Name":"0","AdditionalInformation":"000402","MeasurementName":null},{"CreationTime":"2023-09-26T07:42:35.409015+02:00","Name":"0","AdditionalInformation":"000402","MeasurementName":null},{"CreationTime":"2023-09-26T07:46:19.025434+02:00","Name":"0","AdditionalInformation":"000402","MeasurementName":null},{"CreationTime":"2023-09-26T07:53:00.39757+02:00","Name":"0","AdditionalInformation":"000402","MeasurementName":null},{"CreationTime":"2023-09-26T12:13:05.811852+02:00","Name":"0","AdditionalInformation":"000402","MeasurementName":null},{"CreationTime":"2023-09-26T12:20:55.390404+02:00","Name":"0","AdditionalInformation":"000402","MeasurementName":null},{"CreationTime":"2023-09-26T12:28:22.102606+02:00","Name":"0","AdditionalInformation":"000402","MeasurementName":null},{"CreationTime":"2023-09-26T12:31:44.556936+02:00","Name":"0","AdditionalInformation":"000402","MeasurementName":null},{"CreationTime":"2023-09-26T12:34:47.402819+02:00","Name":"0","AdditionalInformation":"000402","MeasurementName":null},{"CreationTime":"2023-09-26T12:35:58.333718+02:00","Name":"0","AdditionalInformation":"000402","MeasurementName":null},{"CreationTime":"2023-09-26T12:36:58.672022+02:00","Name":"0","AdditionalInformation":"000402","MeasurementName":null},{"CreationTime":"2023-09-27T07:56:55.939027+02:00","Name":"0","AdditionalInformation":"000402","MeasurementName":null},{"CreationTime":"2023-09-27T07:57:48.327018+02:00","Name":"0","AdditionalInformation":"000402","MeasurementName":null},{"CreationTime":"2023-09-27T08:49:22.860251+02:00","Name":"0","AdditionalInformation":"000402","MeasurementName":null},{"CreationTime":"2023-09-28T13:33:22.176447+02:00","Name":"0","AdditionalInformation":"000402","MeasurementName":null},{"CreationTime":"2023-10-03T09:52:48.834862+02:00","Name":"0","AdditionalInformation":"000501","MeasurementName":null},{"CreationTime":"2023-10-03T11:05:33.880078+02:00","Name":"0","AdditionalInformation":"000501","MeasurementName":null},{"CreationTime":"2023-10-03T11:08:10.592477+02:00","Name":"0","AdditionalInformation":"000501","MeasurementName":null},{"CreationTime":"2023-10-04T12:26:06.264175+02:00","Name":"0","AdditionalInformation":"000501","MeasurementName":null},{"CreationTime":"2023-10-04T12:34:46.911632+02:00","Name":"0","AdditionalInformation":"000501","MeasurementName":null},{"CreationTime":"2023-10-04T12:35:14.483897+02:00","Name":"0","AdditionalInformation":"000501","MeasurementName":null},{"CreationTime":"2023-10-04T12:36:59.70424+02:00","Name":"0","AdditionalInformation":"000501","MeasurementName":null},{"CreationTime":"2023-10-05T10:32:58.742519+02:00","Name":"0","AdditionalInformation":"000501","MeasurementName":null},{"CreationTime":"2023-10-05T14:09:25.51797+02:00","Name":"0","AdditionalInformation":"000501","MeasurementName":null},{"CreationTime":"2023-10-05T14:29:06.322803+02:00","Name":"0","AdditionalInformation":"000501","MeasurementName":null},{"CreationTime":"2023-10-06T11:28:14.140285+02:00","Name":"0","AdditionalInformation":"000501","MeasurementName":null},{"CreationTime":"2023-10-06T12:14:18.236125+02:00","Name":"0","AdditionalInformation":"000501","MeasurementName":null},{"CreationTime":"2023-10-06T12:16:47.531895+02:00","Name":"0","AdditionalInformation":"000501","MeasurementName":null},{"CreationTime":"2023-10-06T15:03:04.538194+02:00","Name":"0","AdditionalInformation":"000501","MeasurementName":null},{"CreationTime":"2023-10-06T15:10:00.222264+02:00","Name":"0","AdditionalInformation":"000402","MeasurementName":null},{"CreationTime":"2023-10-09T10:14:35.288962+02:00","Name":"0","AdditionalInformation":"000501","MeasurementName":null},{"CreationTime":"2023-10-09T10:15:05.296724+02:00","Name":"0","AdditionalInformation":"000501","MeasurementName":null},{"CreationTime":"2023-10-09T10:17:13.068285+02:00","Name":"0","AdditionalInformation":"000501","MeasurementName":null},{"CreationTime":"2023-11-03T14:45:02.308128+01:00","Name":"0","AdditionalInformation":"000501","MeasurementName":null},{"CreationTime":"2023-11-20T08:31:33.74511+01:00","Name":"0","AdditionalInformation":"000402","MeasurementName":null},{"CreationTime":"2023-11-27T12:32:26.73728+01:00","Name":"0","AdditionalInformation":"000402","MeasurementName":null},{"CreationTime":"2023-11-27T12:49:40.746095+01:00","Name":"0","AdditionalInformation":"000402","MeasurementName":null},{"CreationTime":"2023-11-28T14:55:07.030062+01:00","Name":"0","AdditionalInformation":"000402","MeasurementName":null},{"CreationTime":"2023-11-28T15:10:36.738612+01:00","Name":"0","AdditionalInformation":"000402","MeasurementName":null},{"CreationTime":"2023-11-29T15:26:19.123594+01:00","Name":"0","AdditionalInformation":"000501","MeasurementName":null},{"CreationTime":"2023-11-06T08:58:38.400567+01:00","Name":"0","AdditionalInformation":"000501","MeasurementName":null},{"CreationTime":"2023-12-01T07:58:40.561906+01:00","Name":"0","AdditionalInformation":"000501","MeasurementName":null},{"CreationTime":"2023-12-06T11:25:06.360488+01:00","Name":"0","AdditionalInformation":"000402","MeasurementName":null},{"CreationTime":"2023-12-11T14:49:55.106773+01:00","Name":"0","AdditionalInformation":"000402","MeasurementName":null},{"CreationTime":"2023-12-11T15:31:17.698753+01:00","Name":"0","AdditionalInformation":"000402","MeasurementName":null},{"CreationTime":"2023-12-11T15:32:07.722984+01:00","Name":"0","AdditionalInformation":"000402","MeasurementName":null},{"CreationTime":"2023-12-11T15:36:56.283242+01:00","Name":"0","AdditionalInformation":"000402","MeasurementName":null},{"CreationTime":"2023-12-11T15:40:19.381142+01:00","Name":"0","AdditionalInformation":"000402","MeasurementName":null},{"CreationTime":"2023-12-13T09:46:26.28116+01:00","Name":"0","AdditionalInformation":"100921","MeasurementName":null},{"CreationTime":"2023-12-05T15:14:38.379846+01:00","Name":"0","AdditionalInformation":"000405","MeasurementName":null},{"CreationTime":"2023-12-13T11:19:25.459404+01:00","Name":"0","AdditionalInformation":"100921","MeasurementName":null},{"CreationTime":"2023-12-13T12:04:30.209611+01:00","Name":"0","AdditionalInformation":"000501","MeasurementName":null},{"CreationTime":"2023-12-14T09:21:02.433518+01:00","Name":"0","AdditionalInformation":"000501","MeasurementName":null},{"CreationTime":"2023-12-21T13:58:59.340805+01:00","Name":"0","AdditionalInformation":"000501","MeasurementName":null},{"CreationTime":"2023-12-22T09:23:04.096413+01:00","Name":"Remote trigger","AdditionalInformation":"000402","MeasurementName":null},{"CreationTime":"2024-01-05T11:00:57.296781+01:00","Name":"A mix of instruments","AdditionalInformation":"100921","MeasurementName":null},{"CreationTime":"2024-01-16T09:34:08.69149+01:00","Name":"402 infra 501 slm","AdditionalInformation":"000402","MeasurementName":null},{"CreationTime":"2024-01-16T09:48:56.29934+01:00","Name":"Project 1","AdditionalInformation":"000501","MeasurementName":null},{"CreationTime":"2024-01-16T11:17:59.760752+01:00","Name":"Project 2","AdditionalInformation":"000501","MeasurementName":null}]